{
  "dct_title_s": "Algérie : Province de Constantine.",
  "dct_description_sm": [
    "1 map on two sheets : dissected and mounted on linen; sheets 57 x 87 and 53 x 87 cm",
    "gravé sur pierre par Erhard-Schièble ; Scale 1:400,000 ; Map originally folded ; Map most likely published by the Depot de la Guerre (France) ; Label pasted on back of both sheets: 'Imprimerie et Librarie Dubos Frères, a Alger, A. Dubos, successeur' ; Relief shown by hachures and spot heights ; Paris : Publisher not identified"
  ],
  "dct_creator_sm": [
    "Erhard (Firm)"
  ],
  "dct_publisher_sm": [
    "Publisher not identified"
  ],
  "schema_provider_s": "Northwestern University",
  "gbl_resourceClass_sm": [
    "Maps"
  ],
  "dct_temporal_sm": [
    "1854"
  ],
  "gbl_indexYear_im": [
    "1854"
  ],
  "gbl_dateRange_drsim": [
    "[1854 TO 1854]"
  ],
  "dct_spatial_sm": [
    "Algeria--Constantine (Wilāyah)",
    "Algeria"
  ],
  "pcdm_memberOf_sm": [
    "64bd8c4c-8e60-4956-b43d-bdc3f93db488"
  ],
  "dct_isPartOf_sm": [
    "15d-01"
  ],
  "dct_rights_sm": [
    "No Copyright - United States",
    "The images on this web site, from maps in the collection of the Melville J. Herskovits Library of African Studies and housed in the Government & Geographic Information Collection of Northwestern University Libraries are in the public domain in the United States, and as such, not subject to copyright restriction. The Libraries request users cite both the URL and Northwestern University Libraries if they wish to reproduce images from the repository. For access to higher resolution images please contact repository@northwestern.edu"
  ],
  "dct_accessRights_s": "Public",
  "dct_references_s": "{\"http://schema.org/url\":\"https://dc.library.northwestern.edu/items/27292f2e-c50c-4a49-a77f-4ac8f022ba4a\",\"http://iiif.io/api/presentation#manifest\":\"https://api.dc.library.northwestern.edu/api/v2/works/27292f2e-c50c-4a49-a77f-4ac8f022ba4a?as=iiif\"}",
  "id": "27292f2e-c50c-4a49-a77f-4ac8f022ba4a",
  "dct_identifier_sm": [
    "9942208254202441",
    "ark:/81985/n2bp00424"
  ],
  "gbl_mdVersion_s": "Aardvark"
}