{
  "dct_title_s": "Açores Insulae",
  "dct_description_sm": [
    "1 map; 30 x 44 cm",
    "Scale approximately 1:1,700,000 (W 29°10ʹ--W 22°20ʹ/N 36°30ʹ--N 41°12ʹ) ; Relief shown pictorially.; 'Longitudo huius descriptionis sumta est à meridiano y Ptolemaei, Occidentem versus.'; 'Privilegio Imp. et Reg. Maiest. necnon Ordinum Belgicor. ad decennium'.; Illustrated with ships and sea monsters.; Latin text on verso with caption title: Asores Insulae; numbered 15."
  ],
  "dct_publisher_sm": [
    "[publisher not identified]"
  ],
  "schema_provider_s": "Northwestern University",
  "gbl_resourceClass_sm": [
    "Maps"
  ],
  "gbl_resourceType_sm": [
    "Early maps"
  ],
  "dct_temporal_sm": [
    "1584"
  ],
  "gbl_indexYear_im": [
    "1584"
  ],
  "gbl_dateRange_drsim": [
    "[1584 TO 1584]"
  ],
  "dct_spatial_sm": [
    "Azores"
  ],
  "locn_geometry": "POLYGON((-29.1667 41.2, -22.3333 41.2, -22.3333 36.5, -29.1667 36.5, -29.1667 41.2))",
  "dcat_bbox": "ENVELOPE(-29.1667,-22.3333,41.2,36.5)",
  "dcat_centroid": "38.85,-25.75",
  "pcdm_memberOf_sm": [
    "64bd8c4c-8e60-4956-b43d-bdc3f93db488"
  ],
  "dct_isPartOf_sm": [
    "15d-01"
  ],
  "dct_rights_sm": [
    "No Copyright - United States",
    "http://rightsstatements.org/vocab/NoC-US/1.0/"
  ],
  "dct_accessRights_s": "Public",
  "dct_references_s": "{\"http://schema.org/url\":\"https://dc.library.northwestern.edu/items/9f1a5512-affa-483f-b65b-98bc45f5f48c\",\"http://iiif.io/api/presentation#manifest\":\"https://api.dc.library.northwestern.edu/api/v2/works/9f1a5512-affa-483f-b65b-98bc45f5f48c?as=iiif\"}",
  "id": "9f1a5512-affa-483f-b65b-98bc45f5f48c",
  "dct_identifier_sm": [
    "9980470463202441",
    "ark:/81985/n2416w04x"
  ],
  "gbl_mdVersion_s": "Aardvark"
}