{
  "dct_title_s": "Africa",
  "dct_description_sm": [
    "1 map : hand colored; 48 x 60 cm",
    "by J. Arrowsmith ; Scale 1:16,500,000 ; Prime meridian: Greenwich ; Boundaries hand-colored ; Relief shown by hachures ; Numbered upper right: '22' ; Detached from : Arrowsmith, J. The London atlas of universal geography. London, 1842-1850 ; London : J. Arrowsmith"
  ],
  "dct_creator_sm": [
    "Arrowsmith, John, 1790-1873"
  ],
  "dct_publisher_sm": [
    "J. Arrowsmith"
  ],
  "schema_provider_s": "Northwestern University",
  "gbl_resourceClass_sm": [
    "Maps"
  ],
  "dct_temporal_sm": [
    "1842"
  ],
  "gbl_indexYear_im": [
    "1842"
  ],
  "gbl_dateRange_drsim": [
    "[1842 TO 1842]"
  ],
  "dct_spatial_sm": [
    "Africa"
  ],
  "pcdm_memberOf_sm": [
    "64bd8c4c-8e60-4956-b43d-bdc3f93db488"
  ],
  "dct_isPartOf_sm": [
    "15d-01"
  ],
  "dct_rights_sm": [
    "No Copyright - United States",
    "The images on this web site, from maps in the collection of the Melville J. Herskovits Library of African Studies and housed in the Government & Geographic Information Collection of Northwestern University Libraries are in the public domain in the United States, and as such, not subject to copyright restriction. The Libraries request users cite both the URL and Northwestern University Libraries if they wish to reproduce images from the repository. For access to higher resolution images please contact repository@northwestern.edu"
  ],
  "dct_accessRights_s": "Public",
  "dct_references_s": "{\"http://schema.org/url\":\"https://dc.library.northwestern.edu/items/e218b503-5ea8-4e8e-ae3c-15a0b16a324f\",\"http://iiif.io/api/presentation#manifest\":\"https://api.dc.library.northwestern.edu/api/v2/works/e218b503-5ea8-4e8e-ae3c-15a0b16a324f?as=iiif\"}",
  "id": "e218b503-5ea8-4e8e-ae3c-15a0b16a324f",
  "dct_identifier_sm": [
    "9940379184202441",
    "ark:/81985/n28g8hj03"
  ],
  "gbl_mdVersion_s": "Aardvark"
}